msguard/__init__.py
msguard/constraints/__init__.py
msguard/constraints/base.py
msguard/constraints/exception.py
msguard/constraints/logic.py
msguard/constraints/path/__init__.py
msguard/constraints/path/builder.py
msguard/constraints/path/path.py
msguard/constraints/path/rule.py
msguard/security/__init__.py
msguard/security/exception.py
msguard/security/hijack.py
msguard/security/injection.py
msguard/security/io.py
msguard/utils/__init__.py
msguard/utils/config.py
msguard/utils/constants.py
msguard/validation/__init__.py
msguard/validation/cli_usage.py
msguard/validation/decorator_usage.py
test/security/test_hijack.py
test/security/test_injection.py
test/security/test_io.py
test/validation/test_cli_usage.py
test/validation/test_decorator_usage.py
msguard-0.0.8.dist-info/METADATA
msguard-0.0.8.dist-info/WHEEL
msguard-0.0.8.dist-info/top_level.txt
msguard-0.0.8.dist-info/RECORD
