Metadata-Version: 2.4
Name: msguard
Version: 0.0.8
Summary: MindStudio Guard Repo
License: Apache-2.0
Project-URL: source, https://gitee.com/ascend/msit/tree/master/msserviceprofiler/msserviceprofiler
Project-URL: documentation, https://gitee.com/ascend/msit/tree/master/msprechecker
Project-URL: tracker, https://gitee.com/ascend/msit/issues
Keywords: ms,guard,security
Classifier: Programming Language :: Python :: 3
Classifier: Programming Language :: Python :: 3.7
Classifier: Programming Language :: Python :: 3.8
Classifier: Programming Language :: Python :: 3.9
Classifier: Programming Language :: Python :: 3.10
Classifier: Programming Language :: Python :: 3.11
Classifier: License :: OSI Approved :: Apache Software License
Classifier: Operating System :: OS Independent
Requires-Python: >=3.7
